bbobax/__init__.py
bbobax/bbob.py
bbobax/descriptor_fns.py
bbobax/fitness_fns.py
bbobax/noise.py
bbobax/types.py
bbobax-0.1.0.dist-info/METADATA
bbobax-0.1.0.dist-info/WHEEL
bbobax-0.1.0.dist-info/licenses/LICENSE
bbobax-0.1.0.dist-info/RECORD
