Metadata-Version: 2.4
Name: bbobax
Version: 0.1.0
Summary: BBOBax: Accelerated Black-Box Optimization Benchmark.
Project-URL: Homepage, https://github.com/maxencefaldor/bbobax
Project-URL: Documentation, https://maxencefaldor.github.io/bbobax/
Author-email: Maxence Faldor <maxencefaldor@gmail.com>
License-Expression: MIT
License-File: LICENSE
Keywords: bbob,benchmark,black-box optimization,quality-diversity
Classifier: License :: OSI Approved :: MIT License
Classifier: Operating System :: OS Independent
Classifier: Programming Language :: Python :: 3.11
Classifier: Programming Language :: Python :: 3.12
Classifier: Programming Language :: Python :: 3.13
Requires-Python: >=3.11
Requires-Dist: flax>=0.12.0
Requires-Dist: jax>=0.8.0
Provides-Extra: dev
Requires-Dist: mypy; extra == 'dev'
Requires-Dist: pytest; extra == 'dev'
Requires-Dist: pytest-cov; extra == 'dev'
Requires-Dist: ruff; extra == 'dev'
Provides-Extra: docs
Requires-Dist: mkdocs; extra == 'docs'
Requires-Dist: mkdocs-jupyter; extra == 'docs'
Requires-Dist: mkdocs-material; extra == 'docs'
Requires-Dist: mkdocstrings[python]; extra == 'docs'
Provides-Extra: notebooks
Requires-Dist: evosax; extra == 'notebooks'
Requires-Dist: ipykernel; extra == 'notebooks'
Requires-Dist: ipywidgets; extra == 'notebooks'
Requires-Dist: mediapy; extra == 'notebooks'
Requires-Dist: scikit-learn; extra == 'notebooks'
